{

"images": [
    "texturemap.png"
],

"framerate": 20,
"frames": [
    [0, 0, 100, 75, 0, 0, 0],
    [100, 0, 100, 75, 0, 0, 0],
    [0, 75, 100, 75, 0, 0, 0],
    [100, 75, 100, 75, 0, 0, 0],
    [0, 150, 226, 178, 0, 0, 0],
    [0, 328, 44, 40, 0, 0, 0],
    [44, 328, 44, 40, 0, 0, 0],
    [88, 328, 20, 30, 0, 0, 0],
    [108, 328, 100, 50, 0, 0, 0],
    [0, 378, 100, 50, 0, 0, 0],
    [100, 378, 100, 50, 0, 0, 0],
    [0, 428, 100, 50, 0, 0, 0],
    [100, 428, 100, 50, 0, 0, 0],
    [0, 478, 62, 63, 0, 0, 0],
    [62, 478, 100, 100, 0, 0, 0],
    [0, 578, 100, 100, 0, 0, 0],
    [100, 578, 20, 30, 0, 0, 0],
    [120, 578, 100, 100, 0, 0, 0],
    [0, 678, 100, 100, 0, 0, 0],
    [100, 678, 100, 100, 0, 0, 0],
    [0, 778, 100, 100, 0, 0, 0],
    [100, 778, 100, 100, 0, 0, 0],
    [0, 878, 100, 100, 0, 0, 0]
],

"animations": {
    "bat1": { "frames": [0] },
    "bat2": { "frames": [1] },
    "bat3": { "frames": [2] },
    "bat4": { "frames": [3] },
    "cloud": { "frames": [4] },
    "coin01": { "frames": [5] },
    "coin02": { "frames": [6] },
    "enemybullet": { "frames": [7] },
    "explosion1": { "frames": [8] },
    "explosion2": { "frames": [9] },
    "explosion3": { "frames": [10] },
    "explosion4": { "frames": [11] },
    "explosion5": { "frames": [12] },
    "island": { "frames": [13] },
    "playbutton": { "frames": [14] },
    "player": { "frames": [15] },
    "playerbullet": { "frames": [16] },
    "playerexplo1": { "frames": [17] },
    "playerexplo2": { "frames": [18] },
    "playerexplo3": { "frames": [19] },
    "playerexplo4": { "frames": [20] },
    "playerexplo5": { "frames": [21] },
    "restartbutton": { "frames": [22] }
},

"texturepacker": [
        "SmartUpdateHash: $TexturePacker:SmartUpdate:0a607905f2800151d5c3caadc5c8cb8d:890ff6b9458a2c82d12395bf8c073725:719597a5782fde2a9214edc9c419f958$",
        "Created with TexturePacker (https://www.codeandweb.com/texturepacker) for EaselJS"
]

}
